[{"date_modified":"20141207","name":"Open Bible Stories","notes":"https://api.unfoldingword.org/obs/txt/1/en/tN-en.json","slug":"obs","source":"https://api.unfoldingword.org/obs/txt/1/en/obs-en.json","status":{"checking_entity":"Distant Shores Media; Wycliffe Associates","checking_level":"3","comments":"Original source text.","contributors":"Distant Shores Media","publish_date":"2014-12-07","source_text":"en","source_text_version":"3.1.1","version":"3.1.1"},"terms":"https://api.unfoldingword.org/obs/txt/1/en/kt-en.json"}]